BPTK_Py/__init__.py
BPTK_Py/bptk.py
BPTK_Py/config/__init__.py
BPTK_Py/config/config.py
BPTK_Py/exceptions/__init__.py
BPTK_Py/exceptions/exceptions.py
BPTK_Py/externalstateadapter/__init__.py
BPTK_Py/externalstateadapter/externalStateAdapter.py
BPTK_Py/externalstateadapter/file_adapter.py
BPTK_Py/externalstateadapter/postgres_adapter.py
BPTK_Py/externalstateadapter/redis_adapter.py
BPTK_Py/logger/__init__.py
BPTK_Py/logger/logfire_adapter.py
BPTK_Py/logger/logfire_usage_example.py
BPTK_Py/logger/logger.py
BPTK_Py/modeling/__init__.py
BPTK_Py/modeling/agent.py
BPTK_Py/modeling/dataCollector.py
BPTK_Py/modeling/event.py
BPTK_Py/modeling/model.py
BPTK_Py/modeling/scheduler.py
BPTK_Py/modeling/simultaneousScheduler.py
BPTK_Py/modeling/datacollectors/__init__.py
BPTK_Py/modeling/datacollectors/agent_datacollector.py
BPTK_Py/modeling/datacollectors/csv_datacollector.py
BPTK_Py/modelmonitor/__init__.py
BPTK_Py/modelmonitor/file_monitor.py
BPTK_Py/modelmonitor/model_monitor.py
BPTK_Py/modelparser/__init__.py
BPTK_Py/modelparser/json_model_parser.py
BPTK_Py/modelparser/meta_model_creator.py
BPTK_Py/modelparser/parser_factory.py
BPTK_Py/scenariomanager/__init__.py
BPTK_Py/scenariomanager/scenario.py
BPTK_Py/scenariomanager/scenario_manager.py
BPTK_Py/scenariomanager/scenario_manager_factory.py
BPTK_Py/scenariomanager/scenario_manager_hybrid.py
BPTK_Py/scenariomanager/scenario_manager_sd.py
BPTK_Py/scenariorunners/__init__.py
BPTK_Py/scenariorunners/hybrid_runner.py
BPTK_Py/scenariorunners/scenario_runner.py
BPTK_Py/scenariorunners/sd_runner.py
BPTK_Py/sdcompiler/compile.py
BPTK_Py/sdcompiler/sdmodel.py
BPTK_Py/sdcompiler/generator/__init__.py
BPTK_Py/sdcompiler/generator/contextBuilder.py
BPTK_Py/sdcompiler/generator/py/__init__.py
BPTK_Py/sdcompiler/generator/py/jinja_template.py
BPTK_Py/sdcompiler/generator/py/py.py
BPTK_Py/sdcompiler/parsers/__init__.py
BPTK_Py/sdcompiler/parsers/smile/__init__.py
BPTK_Py/sdcompiler/parsers/smile/grammar.py
bptk_py-2.2.1.dist-info/licenses/LICENSE
bptk_py-2.2.1.dist-info/METADATA
bptk_py-2.2.1.dist-info/WHEEL
bptk_py-2.2.1.dist-info/top_level.txt
bptk_py-2.2.1.dist-info/RECORD
