Metadata-Version: 2.4
Name: bptk-py
Version: 2.2.1
Summary: A python simulation engine for System Dynamics & Agent based models
Author-email: transentis <support@transentis.com>
Maintainer-email: transentis <support@transentis.com>
Project-URL: Homepage, https://bptk.transentis.com
Project-URL: Documentation, https://bptk.transentis.com
Project-URL: Repository, https://github.com/transentis/bptk_py
Keywords: system dynamics,agent based modeling
Classifier: Programming Language :: Python :: 3
Classifier: License :: OSI Approved :: MIT License
Classifier: Operating System :: OS Independent
Requires-Python: >=3.11
License-File: LICENSE
Requires-Dist: pandas==2.3.0
Requires-Dist: matplotlib==3.10.3
Requires-Dist: scipy==1.15.3
Requires-Dist: numpy==2.3.1
Requires-Dist: ipywidgets==8.1.7
Requires-Dist: xlsxwriter==3.2.5
Requires-Dist: parsimonious==0.10.0
Requires-Dist: xmltodict==0.12.0
Requires-Dist: jinja2==3.1.6
Requires-Dist: sympy==1.14.0
Requires-Dist: distlib==0.3.9
Requires-Dist: cachetools==6.1.0
Requires-Dist: requests==2.32.4
Requires-Dist: flask==3.1.1
Requires-Dist: jsonpickle==4.1.1
Requires-Dist: psycopg==3.2.10
Requires-Dist: redis==6.4.0
Requires-Dist: ujson==5.10.0
Provides-Extra: test
Requires-Dist: pytest; extra == "test"
Requires-Dist: python-dotenv; extra == "test"
Dynamic: license-file
